Metadata-Version: 2.1
Name: byted-overpass-tns-algo-eng-evaluation-hub
Version: 0.0.1
Summary: A simple package named byted_overpass_tns_algo_eng_evaluation_hub
Home-page: https://github.com/artifact/byted_overpass_tns_algo_eng_evaluation_hub.git
Author: artifact
Author-email: artifact@example.com
License: UNKNOWN
Platform: UNKNOWN
Classifier: Programming Language :: Python :: 3
Classifier: License :: OSI Approved :: MIT License
Classifier: Operating System :: OS Independent
